README.rst
setup.py
esprimajs/__init__.py
esprimajs/__main__.py
esprimajs/compiler.py
esprimajs/config.py
esprimajs/context.py
esprimajs/mangler.py
esprimajs/minifier.py
esprimajs/test_export.py
esprimajs/test_import.py
esprimajs/writer.py
esprimajs.egg-info/PKG-INFO
esprimajs.egg-info/SOURCES.txt
esprimajs.egg-info/dependency_links.txt
esprimajs.egg-info/requires.txt
esprimajs.egg-info/top_level.txt
esprimajs/nodes/ArrayExpression.py
esprimajs/nodes/ArrayPattern.py
esprimajs/nodes/ArrowFunctionExpression.py
esprimajs/nodes/AssignmentExpression.py
esprimajs/nodes/AssignmentPattern.py
esprimajs/nodes/BinaryExpression.py
esprimajs/nodes/BlockStatement.py
esprimajs/nodes/BreakStatement.py
esprimajs/nodes/CallExpression.py
esprimajs/nodes/CatchClause.py
esprimajs/nodes/ClassBody.py
esprimajs/nodes/ClassDeclaration.py
esprimajs/nodes/ClassExpression.py
esprimajs/nodes/ConditionalExpression.py
esprimajs/nodes/ContinueStatement.py
esprimajs/nodes/EmptyStatement.py
esprimajs/nodes/ExportAllDeclaration.py
esprimajs/nodes/ExportDefaultDeclaration.py
esprimajs/nodes/ExportNamedDeclaration.py
esprimajs/nodes/ExportSpecifier.py
esprimajs/nodes/ExpressionStatement.py
esprimajs/nodes/ForInStatement.py
esprimajs/nodes/ForOfStatement.py
esprimajs/nodes/ForStatement.py
esprimajs/nodes/FunctionDeclaration.py
esprimajs/nodes/FunctionExpression.py
esprimajs/nodes/Identifier.py
esprimajs/nodes/IfStatement.py
esprimajs/nodes/ImportDeclaration.py
esprimajs/nodes/ImportDefaultSpecifier.py
esprimajs/nodes/ImportNamespaceSpecifier.py
esprimajs/nodes/ImportSpecifier.py
esprimajs/nodes/Literal.py
esprimajs/nodes/LogicalExpression.py
esprimajs/nodes/MemberExpression.py
esprimajs/nodes/MethodDefinition.py
esprimajs/nodes/NewExpression.py
esprimajs/nodes/ObjectExpression.py
esprimajs/nodes/ObjectPattern.py
esprimajs/nodes/Program.py
esprimajs/nodes/Property.py
esprimajs/nodes/RestElement.py
esprimajs/nodes/ReturnStatement.py
esprimajs/nodes/SequenceExpression.py
esprimajs/nodes/Super.py
esprimajs/nodes/SwitchCase.py
esprimajs/nodes/SwitchStatement.py
esprimajs/nodes/TemplateElement.py
esprimajs/nodes/TemplateLiteral.py
esprimajs/nodes/ThisExpression.py
