Metadata-Version: 2.1
Name: esprimajs
Version: 0.1.0
Summary: es6-compatible javascript minifier
Home-page: https://github.com/humkanet/esprimajs
Author: kdmal
Author-email: kdmal@yandex.ru
License: MIT
Platform: UNKNOWN
Classifier: Programming Language :: Python :: 3
Classifier: Operating System :: OS Independent
Requires-Python: >=3
